group_on_email/__init__.py
group_on_email/listeners.py
group_on_email/management/__init__.py
group_on_email/management/commands/__init__.py
group_on_email/management/commands/group_on_email.py
tendenci_group_on_email-0.1.9.dist-info/LICENSE
tendenci_group_on_email-0.1.9.dist-info/METADATA
tendenci_group_on_email-0.1.9.dist-info/WHEEL
tendenci_group_on_email-0.1.9.dist-info/top_level.txt
tendenci_group_on_email-0.1.9.dist-info/RECORD
