Metadata-Version: 2.1
Name: tendenci-group-on-email
Version: 0.1.9
Summary: Apply discounts and permissions to account groups based on email suffix eg. .edu.
Home-page: https://github.com/BenSturmfels/tendenci-group-on-email
Author: Ben Sturmfels
Author-email: ben@sturm.com.au
License: UNKNOWN
Project-URL: Source, https://github.com/BenSturmfels/tendenci-group-on-email
Project-URL: Bug Reports, https://github.com/BenSturmfels/tendenci-group-on-email/issues
Platform: UNKNOWN
Classifier: Development Status :: 4 - Beta
Classifier: Intended Audience :: Developers
Classifier: License :: OSI Approved :: GNU General Public License v3 (GPLv3)
Classifier: Programming Language :: Python :: 3
Requires-Python: >=3.6
